MPHTAD/ADforward.py
MPHTAD/ADreverse.py
MPHTAD/__init__.py
MPHTAD/elementary_func.py
MPHTAD/elementary_func_reverse.py
MPHTAD/optimizer.py
MPHTAD/root_finder.py
MPHTAD/vector_autodiff.py
MPHTAD-1.1.dist-info/LICENSE.txt
MPHTAD-1.1.dist-info/METADATA
MPHTAD-1.1.dist-info/WHEEL
MPHTAD-1.1.dist-info/top_level.txt
MPHTAD-1.1.dist-info/RECORD
