Metadata-Version: 2.1
Name: MPHTAD
Version: 1.1
Summary: A package for automatic differentiation
Home-page: https://github.com/cs107-MPHT/cs107-FinalProject.git
Author: Harvard CS107 Final Project Group MPHTAD
License: UNKNOWN
Platform: UNKNOWN
Classifier: Programming Language :: Python :: 3
Classifier: License :: OSI Approved :: MIT License
Classifier: Operating System :: OS Independent
License-File: LICENSE.txt
Requires-Dist: numpy
